lanparty-1.0.9.dist-info/licenses/LICENSE
localchat/__init__.py
localchat/__main__.py
localchat/client/__init__.py
localchat/client/client.py
localchat/client/commands.py
localchat/client/discovery.py
localchat/client/handlers.py
localchat/client/interface.py
localchat/config/__init__.py
localchat/config/colors.py
localchat/config/defaults.py
localchat/core/__init__.py
localchat/core/network.py
localchat/core/protocol.py
localchat/core/security.py
localchat/core/storage.py
localchat/core/utils.py
localchat/logging/__init__.py
localchat/logging/formatter.py
localchat/logging/logger.py
localchat/server/__init__.py
localchat/server/broadcast.py
localchat/server/commands.py
localchat/server/server.py
localchat/server/session.py
lanparty-1.0.9.dist-info/METADATA
lanparty-1.0.9.dist-info/WHEEL
lanparty-1.0.9.dist-info/entry_points.txt
lanparty-1.0.9.dist-info/top_level.txt
lanparty-1.0.9.dist-info/RECORD
