Metadata-Version: 2.4
Name: lanparty
Version: 1.0.9
Summary: Local chat via LAN
Author: EnderLumi, Leon131211
License: GPL-3.0
Project-URL: Homepage, https://github.com/enderlumi/localchat
Project-URL: Source, https://github.com/enderlumi/localchat
Project-URL: Issues, https://github.com/enderlumi/localchat/issues
Requires-Python: >=3.9
License-File: LICENSE
Requires-Dist: colorama>=0.4.6
Provides-Extra: plus
Requires-Dist: prompt_toolkit; extra == "plus"
Dynamic: license-file
